mkdocs_bootstrap_tables_plugin/__init__.py
mkdocs_bootstrap_tables_plugin/plugin.py
mkdocs_bootstrap_tables_plugin-0.1.1.dist-info/LICENSE
mkdocs_bootstrap_tables_plugin-0.1.1.dist-info/METADATA
mkdocs_bootstrap_tables_plugin-0.1.1.dist-info/WHEEL
mkdocs_bootstrap_tables_plugin-0.1.1.dist-info/entry_points.txt
mkdocs_bootstrap_tables_plugin-0.1.1.dist-info/top_level.txt
mkdocs_bootstrap_tables_plugin-0.1.1.dist-info/RECORD
