Metadata-Version: 2.1
Name: mkdocs-bootstrap-tables-plugin
Version: 0.1.1
Summary: A MkDocs plugin to add bootstrap classes to plan markdown generated tables.
Home-page: https://github.com/byrnereese/mkdocs-bootstrap-tables-plugin
Author: Byrne Reese
Author-email: byrne@majordojo.com
License: MIT
Keywords: mkdocs bootstrap css
Platform: UNKNOWN
Classifier: Development Status :: 4 - Beta
Classifier: Intended Audience :: Developers
Classifier: Intended Audience :: Information Technology
Classifier: License :: OSI Approved :: MIT License
Classifier: Programming Language :: Python
Classifier: Programming Language :: Python :: 3 :: Only
Classifier: Programming Language :: Python :: 3.4
Classifier: Programming Language :: Python :: 3.5
Classifier: Programming Language :: Python :: 3.6
Classifier: Programming Language :: Python :: 3.7
Requires-Python: >=3.5
Requires-Dist: mkdocs (>=1.0.4)
